fstr/__init__.py
fstr/fstr.py
fstr/utils.py
fstr-0.1.0a2.dist-info/LICENSE
fstr-0.1.0a2.dist-info/METADATA
fstr-0.1.0a2.dist-info/WHEEL
fstr-0.1.0a2.dist-info/top_level.txt
fstr-0.1.0a2.dist-info/RECORD
